{
    "url": "https://www12.senado.leg.br/noticias/materias/2022/12/15/divulgado-roteiro-da-posse-presidencial-no-congresso-nacional",
    "titulo": "Divulgado roteiro da posse presidencial no Congresso Nacional",
    "descricao": "Foi divulgado nesta quinta-feira (15) o roteiro da posse do presidente eleito, Luiz Inácio Lula da Silva, marcada para as 15h do dia 1º de janeiro, no Congresso Nacional, com informações sobre a chegada dos empossados, dos Chefes de Estado e de Governo, das demais autoridades e dos convidados.",
    "tags": [],
    "texto": "Foi divulgado nesta quinta-feira (15) o roteiro da posse do presidente eleito, Luiz Inácio Lula da Silva, marcada para as 15h do dia 1º de janeiro, no Congresso Nacional, com informações sobre a chegada dos empossados, dos Chefes de Estado e de Governo, das demais autoridades e dos convidados.\n\n\nTambém define as etapas da sessão, que incluem o compromisso constitucional, a assinatura do termo de posse e os pronunciamentos do presidente da Mesa do Congresso, senador Rodrigo Pacheco, e do presidente empossado.\n\n\nVeja aqui\n.\n\n\nAgência Senado (Reprodução autorizada mediante citação da Agência Senado)",
    "data": "2022-12-19T16:30:59-03:00"
}