{
    "url": "https://www12.senado.leg.br/noticias/materias/2023/08/07/senado-vai-comemorar-o-dia-do-advogado",
    "titulo": "Senado vai comemorar o Dia do Advogado",
    "descricao": "O Plenário do Senado terá    sessão especial    na sexta-feira (11), a partir das 14h, para comemorar o Dia do Advogado. A sessão de homenagem foi requerida pela senadora Soraya Thronicke (Podemos-MS), apoiada por outros senadores.",
    "tags": [
        "Profissões"
    ],
    "texto": "O Plenário do Senado terá \nsessão especial\n na sexta-feira (11), a partir das 14h, para comemorar o Dia do Advogado. A sessão de homenagem foi requerida pela senadora Soraya Thronicke (Podemos-MS), apoiada por outros senadores.\n\n\nO requerimento (\nRQS 61/2023\n) lembra que o Dia do Advogado é celebrado anualmente em 11 de agosto, em homenagem à criação, em 1827, dos dois primeiros cursos de direito do país. Naquele ano foram criadas pelo imperador D. Pedro I a Faculdade de Direito do Largo de São Francisco, em São Paulo, e a Faculdade de Direito de Olinda, em Pernambuco.\n\n\nNas palavras da senadora, os advogados são profissionais que \"defendem a justiça, a liberdade e a cidadania, trabalho que é indispensável para o exercício de uma democracia cada vez mais efetiva\".\n\n\nAgência Senado (Reprodução autorizada mediante citação da Agência Senado)",
    "data": "2023-08-10T13:46:06-03:00"
}